{"code":"2353","institutional":[{"date":"2026-07-13","foreign":-9317,"trust":-1013,"dealer":-389,"total":-10719},{"date":"2026-07-14","foreign":-891,"trust":158,"dealer":635,"total":-98},{"date":"2026-07-15","foreign":13345,"trust":-47,"dealer":1438,"total":14736},{"date":"2026-07-16","foreign":8452,"trust":-145,"dealer":274,"total":8581},{"date":"2026-07-17","foreign":1721,"trust":-4197,"dealer":954,"total":-1522},{"date":"2026-07-20","foreign":2487,"trust":-3817,"dealer":1503,"total":173},{"date":"2026-07-21","foreign":10215,"trust":-3510,"dealer":795,"total":7500},{"date":"2026-07-22","foreign":8454,"trust":-3773,"dealer":-171,"total":4510},{"date":"2026-07-23","foreign":2059,"trust":-3667,"dealer":-221,"total":-1829},{"date":"2026-07-24","foreign":-1043,"trust":107,"dealer":-242,"total":-1178}],"inst5":{"foreign":22172,"trust":-14660,"dealer":1664},"margin":[{"date":"2026-07-09","marginBal":43196,"shortBal":9069},{"date":"2026-07-13","marginBal":43460,"shortBal":9036},{"date":"2026-07-14","marginBal":42945,"shortBal":8591},{"date":"2026-07-15","marginBal":42413,"shortBal":4978},{"date":"2026-07-16","marginBal":42608,"shortBal":3695},{"date":"2026-07-17","marginBal":41862,"shortBal":2570},{"date":"2026-07-20","marginBal":41327,"shortBal":2327},{"date":"2026-07-21","marginBal":40819,"shortBal":2329},{"date":"2026-07-22","marginBal":40313,"shortBal":2265},{"date":"2026-07-23","marginBal":40490,"shortBal":2314}]}