{"code":"3081","institutional":[{"date":"2026-07-09","foreign":-453,"trust":84,"dealer":0,"total":-369},{"date":"2026-07-13","foreign":-292,"trust":52,"dealer":21,"total":-219},{"date":"2026-07-14","foreign":106,"trust":-1,"dealer":-57,"total":48},{"date":"2026-07-15","foreign":-391,"trust":36,"dealer":-263,"total":-618},{"date":"2026-07-16","foreign":141,"trust":-170,"dealer":-64,"total":-93},{"date":"2026-07-17","foreign":667,"trust":-59,"dealer":-20,"total":588},{"date":"2026-07-20","foreign":330,"trust":-326,"dealer":33,"total":37},{"date":"2026-07-21","foreign":-103,"trust":-107,"dealer":-2,"total":-212},{"date":"2026-07-22","foreign":-33,"trust":1,"dealer":48,"total":16},{"date":"2026-07-23","foreign":-419,"trust":8,"dealer":22,"total":-389}],"inst5":{"foreign":442,"trust":-483,"dealer":81},"margin":[{"date":"2026-07-09","marginBal":4617,"shortBal":0},{"date":"2026-07-13","marginBal":4697,"shortBal":0},{"date":"2026-07-14","marginBal":4468,"shortBal":0},{"date":"2026-07-15","marginBal":4621,"shortBal":5},{"date":"2026-07-16","marginBal":4607,"shortBal":9},{"date":"2026-07-17","marginBal":4280,"shortBal":6},{"date":"2026-07-20","marginBal":4147,"shortBal":12},{"date":"2026-07-21","marginBal":4267,"shortBal":15},{"date":"2026-07-22","marginBal":4295,"shortBal":25},{"date":"2026-07-23","marginBal":4413,"shortBal":94}]}