{"code":"5371","institutional":[{"date":"2026-06-08","foreign":-188,"trust":380,"dealer":4,"total":196},{"date":"2026-06-09","foreign":-335,"trust":0,"dealer":9,"total":-326},{"date":"2026-06-10","foreign":-1564,"trust":0,"dealer":12,"total":-1552},{"date":"2026-06-11","foreign":-693,"trust":0,"dealer":-95,"total":-788},{"date":"2026-06-12","foreign":282,"trust":0,"dealer":-3,"total":279},{"date":"2026-06-15","foreign":529,"trust":0,"dealer":28,"total":557},{"date":"2026-06-16","foreign":-170,"trust":0,"dealer":-5,"total":-175},{"date":"2026-06-17","foreign":-164,"trust":0,"dealer":575,"total":411},{"date":"2026-06-18","foreign":629,"trust":-3,"dealer":86,"total":712},{"date":"2026-06-22","foreign":808,"trust":0,"dealer":293,"total":1101}],"inst5":{"foreign":1632,"trust":-3,"dealer":977},"margin":[{"date":"2026-06-05","marginBal":19323,"shortBal":111},{"date":"2026-06-08","marginBal":19138,"shortBal":54},{"date":"2026-06-09","marginBal":19179,"shortBal":128},{"date":"2026-06-10","marginBal":19233,"shortBal":171},{"date":"2026-06-11","marginBal":19243,"shortBal":0},{"date":"2026-06-12","marginBal":19168,"shortBal":0},{"date":"2026-06-15","marginBal":19197,"shortBal":0},{"date":"2026-06-16","marginBal":19225,"shortBal":0},{"date":"2026-06-17","marginBal":19280,"shortBal":6},{"date":"2026-06-18","marginBal":19202,"shortBal":8}]}