{"asof":"2026-06-15 13:18","tz":"台灣時間","quotes":{"3081":{"price":2335.0,"prevClose":2195.0,"chg":140.0,"chgPct":6.38,"time":1781499519,"suffix":".TWO"},"4938":{"price":83.7,"prevClose":93.1,"chg":-9.4,"chgPct":-10.1,"time":1781499525,"suffix":".TW"},"8299":{"price":2305.0,"prevClose":2310.0,"chg":-5.0,"chgPct":-0.22,"time":1781499509,"suffix":".TWO"},"3060":{"price":33.7,"prevClose":31.15,"chg":2.55,"chgPct":8.19,"time":1781499507,"suffix":".TW"},"2357":{"price":793.0,"prevClose":785.0,"chg":8.0,"chgPct":1.02,"time":1781499523,"suffix":".TW"},"2353":{"price":38.35,"prevClose":36.7,"chg":1.65,"chgPct":4.5,"time":1781499517,"suffix":".TW"},"2377":{"price":137.0,"prevClose":136.5,"chg":0.5,"chgPct":0.37,"time":1781499521,"suffix":".TW"},"2376":{"price":343.5,"prevClose":342.0,"chg":1.5,"chgPct":0.44,"time":1781499513,"suffix":".TW"},"2382":{"price":368.5,"prevClose":372.0,"chg":-3.5,"chgPct":-0.94,"time":1781499523,"suffix":".TW"},"3231":{"price":160.5,"prevClose":156.0,"chg":4.5,"chgPct":2.88,"time":1781499525,"suffix":".TW"},"2324":{"price":37.8,"prevClose":36.35,"chg":1.45,"chgPct":3.99,"time":1781499527,"suffix":".TW"},"3017":{"price":2420.0,"prevClose":2405.0,"chg":15.0,"chgPct":0.62,"time":1781499520,"suffix":".TW"},"3324":{"price":1065.0,"prevClose":1055.0,"chg":10.0,"chgPct":0.95,"time":1781499519,"suffix":".TWO"},"3037":{"price":958.0,"prevClose":902.0,"chg":56.0,"chgPct":6.21,"time":1781499528,"suffix":".TW"},"2383":{"price":5025.0,"prevClose":4830.0,"chg":195.0,"chgPct":4.04,"time":1781499496,"suffix":".TW"}}}