{"asof":"2026-06-16 10:38","tz":"台灣時間","quotes":{"3081":{"price":2280.0,"prevClose":2335.0,"chg":-55.0,"chgPct":-2.36,"time":1781576326,"suffix":".TWO"},"4938":{"price":82.4,"prevClose":83.5,"chg":-1.1,"chgPct":-1.32,"time":1781576373,"suffix":".TW"},"8299":{"price":2360.0,"prevClose":2320.0,"chg":40.0,"chgPct":1.72,"time":1781576360,"suffix":".TWO"},"3060":{"price":34.2,"prevClose":33.7,"chg":0.5,"chgPct":1.48,"time":1781576367,"suffix":".TW"},"2357":{"price":791.0,"prevClose":792.0,"chg":-1.0,"chgPct":-0.13,"time":1781576337,"suffix":".TW"},"2353":{"price":38.2,"prevClose":38.45,"chg":-0.25,"chgPct":-0.65,"time":1781576376,"suffix":".TW"},"2377":{"price":137.5,"prevClose":140.0,"chg":-2.5,"chgPct":-1.79,"time":1781576376,"suffix":".TW"},"2376":{"price":349.5,"prevClose":349.5,"chg":0.0,"chgPct":0.0,"time":1781576367,"suffix":".TW"},"2382":{"price":365.5,"prevClose":370.0,"chg":-4.5,"chgPct":-1.22,"time":1781576375,"suffix":".TW"},"3231":{"price":161.0,"prevClose":161.5,"chg":-0.5,"chgPct":-0.31,"time":1781576376,"suffix":".TW"},"2324":{"price":38.25,"prevClose":37.85,"chg":0.4,"chgPct":1.06,"time":1781576375,"suffix":".TW"},"3017":{"price":2395.0,"prevClose":2410.0,"chg":-15.0,"chgPct":-0.62,"time":1781576367,"suffix":".TW"},"3324":{"price":1055.0,"prevClose":1055.0,"chg":0.0,"chgPct":0.0,"time":1781576344,"suffix":".TWO"},"3037":{"price":979.0,"prevClose":960.0,"chg":19.0,"chgPct":1.98,"time":1781576365,"suffix":".TW"},"2383":{"price":5100.0,"prevClose":5030.0,"chg":70.0,"chgPct":1.39,"time":1781576363,"suffix":".TW"},"2327":{"price":964.0,"prevClose":940.0,"chg":24.0,"chgPct":2.55,"time":1781576378,"suffix":".TW"},"2492":{"price":494.0,"prevClose":449.5,"chg":44.5,"chgPct":9.9,"time":1781575331,"suffix":".TW"},"6173":{"price":291.0,"prevClose":304.0,"chg":-13.0,"chgPct":-4.28,"time":1781576378,"suffix":".TWO"},"2428":{"price":287.0,"prevClose":310.0,"chg":-23.0,"chgPct":-7.42,"time":1781576377,"suffix":".TW"},"2472":{"price":348.5,"prevClose":386.0,"chg":-37.5,"chgPct":-9.72,"time":1781576377,"suffix":".TW"},"6175":{"price":101.0,"prevClose":108.0,"chg":-7.0,"chgPct":-6.48,"time":1781576362,"suffix":".TWO"},"2313":{"price":252.5,"prevClose":257.5,"chg":-5.0,"chgPct":-1.94,"time":1781576375,"suffix":".TW"},"6274":{"price":1605.0,"prevClose":1570.0,"chg":35.0,"chgPct":2.23,"time":1781576360,"suffix":".TWO"},"2368":{"price":1340.0,"prevClose":1320.0,"chg":20.0,"chgPct":1.52,"time":1781576374,"suffix":".TW"},"6271":{"price":228.5,"prevClose":244.0,"chg":-15.5,"chgPct":-6.35,"time":1781576366,"suffix":".TW"},"3491":{"price":1645.0,"prevClose":1555.0,"chg":90.0,"chgPct":5.79,"time":1781576358,"suffix":".TWO"},"2314":{"price":16.05,"prevClose":15.7,"chg":0.35,"chgPct":2.23,"time":1781575217,"suffix":".TW"},"6285":{"price":276.0,"prevClose":274.5,"chg":1.5,"chgPct":0.55,"time":1781576362,"suffix":".TW"},"3419":{"price":14.25,"prevClose":14.35,"chg":-0.1,"chgPct":-0.7,"time":1781576298,"suffix":".TW"},"3105":{"price":506.0,"prevClose":511.0,"chg":-5.0,"chgPct":-0.98,"time":1781576369,"suffix":".TWO"},"8086":{"price":158.5,"prevClose":156.0,"chg":2.5,"chgPct":1.6,"time":1781576368,"suffix":".TWO"},"2455":{"price":405.5,"prevClose":369.0,"chg":36.5,"chgPct":9.89,"time":1781576365,"suffix":".TW"},"2059":{"price":6705.0,"prevClose":6960.0,"chg":-255.0,"chgPct":-3.66,"time":1781576370,"suffix":".TW"},"3178":{"price":64.8,"prevClose":64.5,"chg":0.3,"chgPct":0.47,"time":1781575443,"suffix":".TWO"},"3653":{"price":3820.0,"prevClose":3835.0,"chg":-15.0,"chgPct":-0.39,"time":1781576370,"suffix":".TW"},"5388":{"price":85.4,"prevClose":86.5,"chg":-1.1,"chgPct":-1.27,"time":1781576366,"suffix":".TW"},"3596":{"price":187.5,"prevClose":190.5,"chg":-3.0,"chgPct":-1.57,"time":1781576351,"suffix":".TW"},"3665":{"price":2165.0,"prevClose":2265.0,"chg":-100.0,"chgPct":-4.42,"time":1781576379,"suffix":".TW"}}}