{"asof":"2026-07-01 09:42","tz":"台灣時間","quotes":{"3081":{"price":2050.0,"prevClose":2020.0,"chg":30.0,"chgPct":1.49,"time":1782868975,"suffix":".TWO"},"4938":{"price":83.6,"prevClose":83.8,"chg":-0.2,"chgPct":-0.24,"time":1782868970,"suffix":".TW"},"8299":{"price":2355.0,"prevClose":2385.0,"chg":-30.0,"chgPct":-1.26,"time":1782868972,"suffix":".TWO"},"3060":{"price":35.4,"prevClose":36.75,"chg":-1.35,"chgPct":-3.67,"time":1782868975,"suffix":".TW"},"2357":{"price":643.0,"prevClose":700.0,"chg":-57.0,"chgPct":-8.14,"time":1782868981,"suffix":".TW"},"2353":{"price":33.35,"prevClose":33.1,"chg":0.25,"chgPct":0.76,"time":1782868981,"suffix":".TW"},"2377":{"price":143.5,"prevClose":146.0,"chg":-2.5,"chgPct":-1.71,"time":1782868981,"suffix":".TW"},"2376":{"price":344.0,"prevClose":344.0,"chg":0.0,"chgPct":0.0,"time":1782868978,"suffix":".TW"},"2382":{"price":374.0,"prevClose":368.0,"chg":6.0,"chgPct":1.63,"time":1782868980,"suffix":".TW"},"3231":{"price":161.5,"prevClose":158.5,"chg":3.0,"chgPct":1.89,"time":1782868975,"suffix":".TW"},"2324":{"price":35.45,"prevClose":35.3,"chg":0.15,"chgPct":0.42,"time":1782868981,"suffix":".TW"},"3017":{"price":2595.0,"prevClose":2525.0,"chg":70.0,"chgPct":2.77,"time":1782868967,"suffix":".TW"},"3324":{"price":1020.0,"prevClose":1010.0,"chg":10.0,"chgPct":0.99,"time":1782868942,"suffix":".TWO"},"3037":{"price":1100.0,"prevClose":1070.0,"chg":30.0,"chgPct":2.8,"time":1782868982,"suffix":".TW"},"2383":{"price":5485.0,"prevClose":5390.0,"chg":95.0,"chgPct":1.76,"time":1782868931,"suffix":".TW"},"2327":{"price":1190.0,"prevClose":1140.0,"chg":50.0,"chgPct":4.39,"time":1782868983,"suffix":".TW"},"2492":{"price":600.0,"prevClose":565.0,"chg":35.0,"chgPct":6.19,"time":1782868811,"suffix":".TW"},"6173":{"price":341.5,"prevClose":310.5,"chg":31.0,"chgPct":9.98,"time":1782868923,"suffix":".TWO"},"2428":{"price":331.5,"prevClose":315.0,"chg":16.5,"chgPct":5.24,"time":1782868983,"suffix":".TW"},"2472":{"price":475.0,"prevClose":453.5,"chg":21.5,"chgPct":4.74,"time":1782868983,"suffix":".TW"},"6175":{"price":117.5,"prevClose":112.5,"chg":5.0,"chgPct":4.44,"time":1782868982,"suffix":".TWO"},"2313":{"price":231.5,"prevClose":232.5,"chg":-1.0,"chgPct":-0.43,"time":1782868983,"suffix":".TW"},"6274":{"price":1685.0,"prevClose":1680.0,"chg":5.0,"chgPct":0.3,"time":1782868975,"suffix":".TWO"},"3491":{"price":1330.0,"prevClose":1335.0,"chg":-5.0,"chgPct":-0.37,"time":1782868939,"suffix":".TWO"},"2314":{"price":14.0,"prevClose":15.45,"chg":-1.45,"chgPct":-9.39,"time":1782867730,"suffix":".TW"},"6285":{"price":256.5,"prevClose":259.5,"chg":-3.0,"chgPct":-1.16,"time":1782868956,"suffix":".TW"},"2481":{"price":197.0,"prevClose":182.5,"chg":14.5,"chgPct":7.95,"time":1782868938,"suffix":".TW"},"5425":{"price":124.5,"prevClose":120.5,"chg":4.0,"chgPct":3.32,"time":1782868806,"suffix":".TWO"},"3675":{"price":393.0,"prevClose":378.0,"chg":15.0,"chgPct":3.97,"time":1782868801,"suffix":".TWO"},"8255":{"price":190.0,"prevClose":184.0,"chg":6.0,"chgPct":3.26,"time":1782868978,"suffix":".TWO"},"3317":{"price":92.3,"prevClose":89.4,"chg":2.9,"chgPct":3.24,"time":1782868982,"suffix":".TWO"},"6435":{"price":382.5,"prevClose":363.5,"chg":19.0,"chgPct":5.23,"time":1782868980,"suffix":".TWO"},"8261":{"price":297.5,"prevClose":270.5,"chg":27.0,"chgPct":9.98,"time":1782868964,"suffix":".TW"},"5299":{"price":127.5,"prevClose":123.0,"chg":4.5,"chgPct":3.66,"time":1782868964,"suffix":".TWO"},"6138":{"price":395.0,"prevClose":368.0,"chg":27.0,"chgPct":7.34,"time":1782868985,"suffix":".TWO"},"6719":{"price":297.0,"prevClose":270.0,"chg":27.0,"chgPct":10.0,"time":1782868976,"suffix":".TW"},"3707":{"price":89.7,"prevClose":86.9,"chg":2.8,"chgPct":3.22,"time":1782868985,"suffix":".TWO"},"3016":{"price":133.5,"prevClose":133.5,"chg":0.0,"chgPct":0.0,"time":1782868985,"suffix":".TW"},"5347":{"price":215.5,"prevClose":216.0,"chg":-0.5,"chgPct":-0.23,"time":1782868985,"suffix":".TWO"},"1536":{"price":48.3,"prevClose":47.7,"chg":0.6,"chgPct":1.26,"time":1782868983,"suffix":".TW"},"2049":{"price":345.0,"prevClose":325.0,"chg":20.0,"chgPct":6.15,"time":1782868985,"suffix":".TW"},"4576":{"price":219.0,"prevClose":211.0,"chg":8.0,"chgPct":3.79,"time":1782868957,"suffix":".TW"},"4583":{"price":604.0,"prevClose":594.0,"chg":10.0,"chgPct":1.68,"time":1782868978,"suffix":".TW"},"4571":{"price":168.5,"prevClose":167.0,"chg":1.5,"chgPct":0.9,"time":1782868934,"suffix":".TW"},"1597":{"price":145.5,"prevClose":141.0,"chg":4.5,"chgPct":3.19,"time":1782868985,"suffix":".TW"},"3019":{"price":143.5,"prevClose":142.5,"chg":1.0,"chgPct":0.7,"time":1782868971,"suffix":".TW"},"3362":{"price":192.5,"prevClose":189.0,"chg":3.5,"chgPct":1.85,"time":1782868982,"suffix":".TWO"},"2374":{"price":75.8,"prevClose":75.0,"chg":0.8,"chgPct":1.07,"time":1782868964,"suffix":".TW"},"5371":{"price":91.3,"prevClose":86.9,"chg":4.4,"chgPct":5.06,"time":1782868986,"suffix":".TWO"},"2464":{"price":188.5,"prevClose":173.0,"chg":15.5,"chgPct":8.96,"time":1782868986,"suffix":".TW"},"2308":{"price":2005.0,"prevClose":1950.0,"chg":55.0,"chgPct":2.82,"time":1782868975,"suffix":".TW"},"8374":{"price":87.0,"prevClose":85.0,"chg":2.0,"chgPct":2.35,"time":1782868975,"suffix":".TW"},"4585":{"price":305.0,"prevClose":300.5,"chg":4.5,"chgPct":1.5,"time":1782868921,"suffix":".TW"},"6667":{"price":271.5,"prevClose":268.0,"chg":3.5,"chgPct":1.31,"time":1782868979,"suffix":".TWO"},"6230":{"price":126.5,"prevClose":124.0,"chg":2.5,"chgPct":2.02,"time":1782868951,"suffix":".TW"},"3653":{"price":3470.0,"prevClose":3430.0,"chg":40.0,"chgPct":1.17,"time":1782868870,"suffix":".TW"},"8996":{"price":1565.0,"prevClose":1550.0,"chg":15.0,"chgPct":0.97,"time":1782868804,"suffix":".TW"},"2421":{"price":147.0,"prevClose":142.0,"chg":5.0,"chgPct":3.52,"time":1782868975,"suffix":".TW"},"6531":{"price":960.0,"prevClose":998.0,"chg":-38.0,"chgPct":-3.81,"time":1782868987,"suffix":".TW"},"2344":{"price":199.5,"prevClose":207.5,"chg":-8.0,"chgPct":-3.86,"time":1782868987,"suffix":".TW"},"5289":{"price":1575.0,"prevClose":1615.0,"chg":-40.0,"chgPct":-2.48,"time":1782868982,"suffix":".TWO"},"2408":{"price":440.0,"prevClose":452.5,"chg":-12.5,"chgPct":-2.76,"time":1782868987,"suffix":".TW"},"2337":{"price":150.0,"prevClose":155.5,"chg":-5.5,"chgPct":-3.54,"time":1782868987,"suffix":".TW"},"3260":{"price":404.0,"prevClose":409.0,"chg":-5.0,"chgPct":-1.22,"time":1782868981,"suffix":".TWO"},"4967":{"price":257.5,"prevClose":263.5,"chg":-6.0,"chgPct":-2.28,"time":1782868974,"suffix":".TW"},"2451":{"price":259.0,"prevClose":266.5,"chg":-7.5,"chgPct":-2.81,"time":1782868977,"suffix":".TW"},"5351":{"price":83.2,"prevClose":86.8,"chg":-3.6,"chgPct":-4.15,"time":1782868988,"suffix":".TWO"},"0050":{"price":109.55,"prevClose":107.8,"chg":1.75,"chgPct":1.62,"time":1782868987,"suffix":".TW"},"00981A":{"price":32.09,"prevClose":31.28,"chg":0.81,"chgPct":2.59,"time":1782868986,"suffix":".TW"},"00631L":{"price":39.57,"prevClose":38.42,"chg":1.15,"chgPct":2.99,"time":1782868989,"suffix":".TW"},"00632R":{"price":9.83,"prevClose":9.94,"chg":-0.11,"chgPct":-1.11,"time":1782868989,"suffix":".TW"}}}