{"asof": "07/02", "groups": [{"key": "hdd", "icon": "💽", "title": "HDD / 儲存", "note": "AI 資料中心大容量硬碟需求(對應台股 銘異3060)", "stocks": [{"tk": "STX", "name": "希捷", "desc": "HDD 雙雄之一・HAMR 近線大容量硬碟龍頭", "price": 820.16, "chgPct": -10.38, "date": "07/02"}, {"tk": "WDC", "name": "威騰", "desc": "HDD 雙雄之一(+ 快閃記憶體事業)", "price": 539.0, "chgPct": -9.92, "date": "07/02"}, {"tk": "NTAP", "name": "NetApp", "desc": "企業級儲存陣列(混合雲/資料管理)", "price": 154.17, "chgPct": -1.41, "date": "07/02"}, {"tk": "HPE", "name": "慧與科技", "desc": "伺服器 / 儲存系統(HPE・企業資料中心)", "price": 41.23, "chgPct": -6.19, "date": "07/02"}, {"tk": "MRVL", "name": "邁威爾", "desc": "HDD 控制晶片 + 資料中心/光電互聯", "price": 245.29, "chgPct": -9.84, "date": "07/02"}, {"tk": "DELL", "name": "戴爾", "desc": "伺服器 / 儲存系統整機", "price": 394.32, "chgPct": -7.27, "date": "07/02"}]}, {"key": "power", "icon": "⚡", "title": "功率元件 / 電源", "note": "功率半導體漲價循環 + AI 伺服器供電(對應台股 強茂/大中/富鼎等)", "stocks": [{"tk": "MPWR", "name": "MPS", "desc": "電源管理 / DrMOS・AI 伺服器供電核心 ⭐", "price": 1288.16, "chgPct": -3.27, "date": "07/02"}, {"tk": "ON", "name": "onsemi", "desc": "功率 MOSFET / IGBT / SiC(車用・工控)", "price": 91.22, "chgPct": -3.6, "date": "07/02"}, {"tk": "WOLF", "name": "Wolfspeed", "desc": "碳化矽 SiC 純製造商(高壓功率)", "price": 40.0, "chgPct": -10.23, "date": "07/02"}, {"tk": "NVTS", "name": "Navitas", "desc": "氮化鎵 GaN 功率 IC(快充/伺服器電源)", "price": 14.46, "chgPct": -12.52, "date": "07/02"}, {"tk": "POWI", "name": "Power Integ", "desc": "高壓電源轉換 IC", "price": 72.99, "chgPct": -9.07, "date": "07/02"}, {"tk": "VICR", "name": "Vicor", "desc": "電源模組(資料中心 HVDC 高壓直流供電)", "price": 282.95, "chgPct": -19.21, "date": "07/02"}, {"tk": "DIOD", "name": "Diodes", "desc": "分離式 / 功率二極體・MOSFET", "price": 96.25, "chgPct": -8.67, "date": "07/02"}, {"tk": "ADI", "name": "亞德諾", "desc": "類比 / 電源管理大廠", "price": 377.16, "chgPct": -3.04, "date": "07/02"}, {"tk": "TXN", "name": "德儀", "desc": "類比 / 電源管理大廠", "price": 293.08, "chgPct": -1.79, "date": "07/02"}, {"tk": "NXPI", "name": "恩智浦", "desc": "車用 / 功率 / 微控制器", "price": 273.36, "chgPct": -2.08, "date": "07/02"}]}]}